[
    {
        "code": "06021",
        "cost": 4,
        "deck_limit": 3,
        "faction_code": "stark",
        "illustrator": "",
        "is_intrigue": false,
        "is_loyal": false,
        "is_military": true,
        "is_power": true,
        "is_unique": false,
        "name": "Bear Island Host",
        "octgn_id": null,
        "pack_code": "GtR",
        "position": 21,
        "quantity": 3,
        "strength": 4,
        "text": "Bestow (3). No attachments.\n<b>Action:</b> Discard 1 gold from Bear Island Host to choose a <i>House Mormont</i> character. Until the end of the phase, that character does not kneel when declared as an attacker in a [military] challenge.",
        "traits": "Army. House Mormont.",
        "type_code": "character"
    },
    {
        "code": "06022",
        "cost": 3,
        "deck_limit": 3,
        "faction_code": "stark",
        "illustrator": "",
        "is_loyal": true,
        "is_unique": false,
        "name": "Marriage Pact",
        "octgn_id": null,
        "pack_code": "GtR",
        "position": 22,
        "quantity": 3,
        "text": "Terminal.\nAttached character cannot participate in challenges against you.\n<b>Forced Interrupt:</b> When attached character leaves play, sacrifice a character you control.",
        "traits": "Condition.",
        "type_code": "attachment"
    },
    {
        "code": "06023",
        "cost": 3,
        "deck_limit": 3,
        "faction_code": "tyrell",
        "illustrator": "",
        "is_intrigue": true,
        "is_loyal": false,
        "is_military": true,
        "is_power": false,
        "is_unique": false,
        "name": "Knight of the Reach",
        "octgn_id": null,
        "pack_code": "GtR",
        "position": 23,
        "quantity": 3,
        "strength": 3,
        "text": "<b>Reaction:</b> After you win a challenge in which Knight of the Reach is attacking or defending alone, choose a <i>Lady</i> character. That character gains 1 power.",
        "traits": "Knight.",
        "type_code": "character"
    },
    {
        "code": "06024",
        "cost": 1,
        "deck_limit": 3,
        "faction_code": "tyrell",
        "illustrator": "",
        "is_loyal": false,
        "is_unique": false,
        "name": "\"Lord Renly's Ride\"",
        "octgn_id": null,
        "pack_code": "GtR",
        "position": 24,
        "quantity": 3,
        "text": "<b>Action:</b> Choose a character. Until the end of the phase, that character gets +X STR and gains intimidate. X is the printed STR of the top character in your dead pile.",
        "traits": "Song.",
        "type_code": "event"
    },
    {
        "code": "06025",
        "cost": 2,
        "deck_limit": 3,
        "faction_code": "thenightswatch",
        "illustrator": "",
        "is_intrigue": true,
        "is_loyal": false,
        "is_military": false,
        "is_power": true,
        "is_unique": true,
        "name": "Gilly",
        "octgn_id": null,
        "pack_code": "GtR",
        "position": 25,
        "quantity": 3,
        "strength": 1,
        "text": "Bestow(3).\n<b>Action:</b> Discard 1 gold from Gilly to choose a <i>Steward</i> character you control. Until the end of the phase, that character gains stealth.",
        "traits": "Wildling.",
        "type_code": "character"
    },
    {
        "code": "06026",
        "cost": 2,
        "deck_limit": 3,
        "faction_code": "thenightswatch",
        "illustrator": "",
        "is_loyal": true,
        "is_unique": false,
        "name": "Guarding the Realm",
        "octgn_id": null,
        "pack_code": "GtR",
        "position": 26,
        "quantity": 3,
        "text": "<b>Marshaling Action:</b> Choose a character with printed cost 3 or lower in an opponent's discard pile, and put it into play under your control.\n<b>Reaction:</b> After you win a challenge as the defending player, pay 1 gold to return Guarding the Realm from your discard pile to your hand.",
        "traits": "",
        "type_code": "event"
    },
    {
        "code": "06027",
        "cost": 7,
        "deck_limit": 3,
        "faction_code": "baratheon",
        "flavor": "\"We choose light or we choose darkness. We choose good or we choose evil. We choose the true god or the false.\"",
        "illustrator": "Nicholas Elias",
        "is_intrigue": true,
        "is_loyal": true,
        "is_military": false,
        "is_power": true,
        "is_unique": true,
        "name": "Melisandre",
        "octgn_id": null,
        "pack_code": "GtR",
        "position": 27,
        "quantity": 3,
        "strength": 6,
        "text": "Insight.\n<b>Reaction:</b> After you win dominance, choose an opponent and look at his or her hand. Then, choose and discard 1 card from that hand. If that card is a character, place it in its owner's dead pile.",
        "traits": "Lady. R'hllor.",
        "type_code": "character"
    },
    {
        "code": "06028",
        "cost": 2,
        "deck_limit": 3,
        "faction_code": "baratheon",
        "flavor": "\"Lead us from the darkness, O my Lord. Fill our hearts with fire, so we may walk your shining path.\"",
        "illustrator": "Sergey Glushakov",
        "is_loyal": false,
        "is_unique": false,
        "name": "Light of the Lord",
        "octgn_id": null,
        "pack_code": "GtR",
        "position": 28,
        "quantity": 3,
        "text": "[baratheon] or <i>R'hllor</i> character only.\n<b>Reaction:</b> After the dominance phase begins, stand attached character and gain 1 gold.",
        "traits": "Blessing. R'hllor.",
        "type_code": "attachment"
    },
    {
        "code": "06029",
        "cost": 3,
        "deck_limit": 3,
        "faction_code": "lannister",
        "illustrator": "",
        "is_intrigue": true,
        "is_loyal": false,
        "is_military": true,
        "is_power": false,
        "is_unique": true,
        "name": "Polliver",
        "octgn_id": null,
        "pack_code": "GtR",
        "position": 29,
        "quantity": 3,
        "strength": 3,
        "text": "Pillage.\n<b>Reaction:</b> After Polliver discards a character using pillage, return 2 gold from the losing opponent's gold pool to the treasury.",
        "traits": "Ally.",
        "type_code": "character"
    },
    {
        "code": "06030",
        "cost": 2,
        "deck_limit": 3,
        "faction_code": "lannister",
        "illustrator": "",
        "is_loyal": false,
        "is_unique": true,
        "name": "The Hand's Solar",
        "octgn_id": null,
        "pack_code": "GtR",
        "position": 30,
        "quantity": 3,
        "text": "<b>Action:</b> Kneel The Hand's Solar to choose a character. Until the end of the phase, that character gains an intrigue icon.",
        "traits": "King's Landing.",
        "type_code": "location"
    },
    {
        "code": "06031",
        "cost": 2,
        "deck_limit": 3,
        "faction_code": "greyjoy",
        "is_intrigue": true,
        "is_loyal": false,
        "is_military": true,
        "is_power": false,
        "is_unique": true,
        "name": "Wex Pyke",
        "octgn_id": null,
        "pack_code": "GtR",
        "position": 31,
        "quantity": 3,
        "strength": 2,
        "text": "Bestow (8).\nWhile Wex Pyke is attacking, each character with printed cost X cannot be declared as a defender. X is the number of gold Wex Pyke has.\n<b>Dominance Action:</b> Move 1 gold from your gold pool to Wex Pyke. (Limit twice per phase.)",
        "traits": "Bastard. House Botley.",
        "type_code": "character"
    },
    {
        "code": "06032",
        "cost": 2,
        "deck_limit": 3,
        "faction_code": "greyjoy",
        "illustrator": "",
        "is_loyal": true,
        "is_unique": false,
        "name": "Iron Islands Market",
        "octgn_id": null,
        "pack_code": "GtR",
        "position": 32,
        "quantity": 3,
        "text": "Limited.\n<b>Marshaling Action:</b> Kneel Iron Islands Market to gain 1 gold. (2 gold instead if an opponent has 8 or more cards in his or her discard pile.)",
        "traits": "Iron Islands.",
        "type_code": "location"
    },
    {
        "code": "06033",
        "cost": 3,
        "deck_limit": 3,
        "faction_code": "targaryen",
        "is_intrigue": false,
        "is_loyal": false,
        "is_military": true,
        "is_power": true,
        "is_unique": false,
        "name": "Second Sons",
        "octgn_id": null,
        "pack_code": "GtR",
        "position": 33,
        "quantity": 3,
        "strength": 6,
        "text": "Bestow(3).\n<b>Forced Interrupt:</b> When the challenges phase ends, sacrifice Second Sons unless you discard 1 gold from it.",
        "traits": "Mercenary.",
        "type_code": "character"
    },
    {
        "code": "06034",
        "cost": 2,
        "deck_limit": 3,
        "faction_code": "targaryen",
        "illustrator": "",
        "is_loyal": true,
        "is_unique": false,
        "name": "A Dragon Is No Slave",
        "octgn_id": null,
        "pack_code": "GtR",
        "position": 34,
        "quantity": 3,
        "text": "<b>Challenges Action:</b> Choose a character without attachments. That character gets -2 STR until the end of the phase.\n<b>Reaction:</b> After you win a challenge in which you control a participating <i>Dragon</i> character or Daenerys Targaryen, pay 1 gold to return A Dragon Is No Slave from your discard pile to your hand.",
        "traits": "",
        "type_code": "event"
    },
    {
        "code": "06035",
        "cost": 2,
        "deck_limit": 3,
        "faction_code": "martell",
        "is_intrigue": false,
        "is_loyal": false,
        "is_military": false,
        "is_power": true,
        "is_unique": false,
        "name": "Orphan of the Greenblood",
        "octgn_id": null,
        "pack_code": "GtR",
        "position": 35,
        "quantity": 3,
        "strength": 2,
        "text": "Bestow(3).\n<b>Action:</b> Discard 1 gold from Orphan of the Greenblood to return another character you control to its owner's hand.",
        "traits": "Ally.",
        "type_code": "character"
    },
    {
        "code": "06036",
        "cost": 1,
        "deck_limit": 3,
        "faction_code": "martell",
        "illustrator": "",
        "is_loyal": false,
        "is_unique": false,
        "name": "Scorching Deserts",
        "octgn_id": null,
        "pack_code": "GtR",
        "position": 36,
        "quantity": 3,
        "text": "<b>Reaction:</b> After a character with fewer than 2 challenge icons is declared as an attacker or defender, kneel and sacrifice Scorching Deserts to remove that character from the challenge.",
        "traits": "Dorne.",
        "type_code": "location"
    },
    {
        "code": "06037",
        "cost": 4,
        "deck_limit": 3,
        "faction_code": "neutral",
        "is_intrigue": true,
        "is_loyal": false,
        "is_military": true,
        "is_power": false,
        "is_unique": true,
        "name": "Black Walder",
        "octgn_id": null,
        "pack_code": "GtR",
        "position": 37,
        "quantity": 3,
        "strength": 5,
        "text": "Bestow(3).\nDuring the third challenge you initiate each phase, Black Walder gains renown and gets +2 STR for each gold he has.",
        "traits": "House Frey.",
        "type_code": "character"
    },
    {
        "code": "06038",
        "cost": 1,
        "deck_limit": 3,
        "faction_code": "neutral",
        "illustrator": "",
        "is_loyal": false,
        "is_unique": false,
        "name": "Great Hall",
        "octgn_id": null,
        "pack_code": "GtR",
        "position": 38,
        "quantity": 3,
        "text": "Limited.\n<b>Marshaling Action:</b> Kneel Great Hall to reduce the cost of the next unique character you marshal this phase by 1. (By 2 instead if that character's printed cost is 6 or higher.)",
        "traits": "Westeros.",
        "type_code": "location"
    },
    {
        "code": "06039",
        "cost": 1,
        "deck_limit": 3,
        "faction_code": "neutral",
        "illustrator": "",
        "is_loyal": false,
        "is_unique": false,
        "name": "\"The Dornishman's Wife\"",
        "octgn_id": null,
        "pack_code": "GtR",
        "position": 39,
        "quantity": 3,
        "text": "<b>Action:</b> Choose an opponent. If that player has a higher power total than you, gain 2 gold. If that player has more cards in his or her hand than you, gain 1 power for your faction. If that player controls more characters than you, draw 1 card.",
        "traits": "Song.",
        "type_code": "event"
    },
    {
        "claim": 1,
        "code": "06040",
        "deck_limit": 2,
        "faction_code": "neutral",
        "illustrator": "",
        "income": 4,
        "initiative": 4,
        "is_loyal": false,
        "is_unique": false,
        "name": "The Annals of Castle Black",
        "octgn_id": "",
        "pack_code": "GtR",
        "position": 40,
        "quantity": 3,
        "reserve": 7,
        "text": "Each player may play events in his or her discard pile as if they were in his or her hand.\n<b>Forced Reaction:</b> After an event is placed in a discard pile, remove it from the game.\n<b>Card design by 2014 Overall World Champion, Alexander Hynes.</b>",
        "traits": "Legacy.",
        "type_code": "plot"
    }
]
