[
    {
        "code": "06103",
        "cost": 2,
        "deck_limit": 3,
        "faction_code": "tyrell",
        "illustrator": "",
        "is_intrigue": true,
        "is_loyal": false,
        "is_military": false,
        "is_power": true,
        "is_unique": false,
        "name": "Highgarden Minstrel",
        "octgn_id": null,
        "pack_code": "TBWB",
        "position": 103,
        "quantity": 3,
        "strength": 1,
        "text": "<b>Reaction:</b> After you play a <i>Song</i> event, gain 1 gold. (Limit 3 times per round.)",
        "traits": "Minstrel.",
        "type_code": "character"
    },
    {
        "code": "06105",
        "cost": 4,
        "deck_limit": 3,
        "faction_code": "thenightswatch",
        "illustrator": "",
        "is_intrigue": true,
        "is_loyal": false,
        "is_military": true,
        "is_power": false,
        "is_unique": true,
        "name": "Donal Noye",
        "octgn_id": null,
        "pack_code": "TBWB",
        "position": 105,
        "quantity": 3,
        "strength": 4,
        "text": "Bestow (3). No attachments except <i>Weapon</i>.\n<b>Action:</b> Discard 1 gold from Donal Noye to put a <i>Weapon</i> attachment into play from your hand.",
        "traits": "Steward.",
        "type_code": "character"
    },
    {
        "code": "06106",
        "cost": 2,
        "deck_limit": 3,
        "faction_code": "thenightswatch",
        "illustrator": "",
        "is_loyal": false,
        "is_unique": false,
        "name": "Ranger's Bow",
        "octgn_id": null,
        "pack_code": "TBWB",
        "position": 106,
        "quantity": 3,
        "text": "[thenightswatch] character only.\nAttached character gets +1 STR.\n<b>Challenges Action:</b> Kneel Ranger's Bow to choose a defending [thenightswatch] character. Until the end of the challenge, that character gets +2 STR.",
        "traits": "Weapon.",
        "type_code": "attachment"
    },
    {
        "code": "06112",
        "cost": 2,
        "deck_limit": 3,
        "faction_code": "greyjoy",
        "illustrator": "",
        "is_loyal": true,
        "is_unique": false,
        "name": "Pay The Iron Price",
        "octgn_id": null,
        "pack_code": "TBWB",
        "position": 112,
        "quantity": 3,
        "text": "<b>Challenges Action:</b> Choose an attachment in an opponent's discard pile, and put it into play under your control.\n<b>Reaction:</b> After you win an unopposed challenge, pay 1 gold to return Pay The Iron Price from your discard pile to your hand.",
        "traits": "",
        "type_code": "event"
    },
    {
        "code": "06113",
        "cost": 2,
        "deck_limit": 3,
        "faction_code": "targaryen",
        "illustrator": "",
        "is_intrigue": true,
        "is_loyal": false,
        "is_military": false,
        "is_power": true,
        "is_unique": false,
        "name": "Freedmen",
        "octgn_id": null,
        "pack_code": "TBWB",
        "position": 113,
        "quantity": 3,
        "strength": 1,
        "text": "<b>Reaction:</b> After you win a challenge by 5 or more STR as the attacking player, put Freedmen into play from your discard pile.",
        "traits": "Ally.",
        "type_code": "character"
    },
    {
        "code": "06114",
        "cost": 2,
        "deck_limit": 3,
        "faction_code": "targaryen",
        "illustrator": "",
        "is_loyal": false,
        "is_unique": false,
        "name": "Warrior's Braid",
        "octgn_id": null,
        "pack_code": "TBWB",
        "position": 114,
        "quantity": 3,
        "text": "[targaryen] character only.\nAttached character gains renown, and gets +1 STR for each bell token on Warrior's Braid.\n<b>Reaction:</b> After you win a [military] challenge in which attached character is attacking, plcae a bell token on Warrior's Braid.",
        "traits": "Item.",
        "type_code": "attachment"
    },
    {
        "code": "06115",
        "cost": 3,
        "deck_limit": 3,
        "faction_code": "martell",
        "illustrator": "",
        "is_intrigue": true,
        "is_loyal": false,
        "is_military": true,
        "is_power": false,
        "is_unique": false,
        "name": "Dornish Spy",
        "octgn_id": null,
        "pack_code": "TBWB",
        "position": 115,
        "quantity": 3,
        "strength": 3,
        "text": "Ambush (4).\n<b>Reaction:</b> After Dornish Spy enters play, choose a character. Until the end of the phase, that character loses a challenge icon of your choice.",
        "traits": "Spy.",
        "type_code": "character"
    },
    {
        "code": "06116",
        "cost": 3,
        "deck_limit": 3,
        "faction_code": "martell",
        "flavor": "Hers was a gentle prison.",
        "illustrator": "",
        "is_loyal": false,
        "is_unique": false,
        "name": "Locked Away",
        "octgn_id": null,
        "pack_code": "TBWB",
        "position": 116,
        "quantity": 3,
        "text": "Terminal.\n<b>Reaction:</b> After the marshaling phase begins, return attached character to its owner's hand (cannot be saved).",
        "traits": "Condition.",
        "type_code": "attachment"
    },
    {
        "code": "06117",
        "cost": 7,
        "deck_limit": 3,
        "faction_code": "neutral",
        "illustrator": "Joel Hustak",
        "is_intrigue": false,
        "is_loyal": false,
        "is_military": true,
        "is_power": true,
        "is_unique": true,
        "name": "Beric Dondarrion",
        "octgn_id": null,
        "pack_code": "TBWB",
        "position": 117,
        "quantity": 3,
        "strength": null,
        "text": "Renown.\nX is the number of kiss tokens Beric Dondarrion has.\n<b>Forced Reaction:</b> After you marshal Beric Dondarrion, place 6 kiss tokens on him. (Cannot be cancelled.)\n<b>Interrupt:</b> When Beric Dondarrion would be killed, discard a kiss token from him to save him.\n<b>Card design by 2014 European Melee Champion, Jakob Hultman.</b>",
        "traits": "Knight. Lord. R'hllor.",
        "type_code": "character"
    },
    {
        "code": "06118",
        "cost": 0,
        "deck_limit": 3,
        "faction_code": "neutral",
        "illustrator": "",
        "is_loyal": false,
        "is_unique": false,
        "name": "Unbridled Generosity",
        "octgn_id": null,
        "pack_code": "TBWB",
        "position": 118,
        "quantity": 3,
        "text": "<b>Action:</b> Choose up to 3 cards. Move 1 gold from the treasury to each of those cards.",
        "traits": "",
        "type_code": "event"
    },
    {
        "code": "06119",
        "deck_limit": 1,
        "faction_code": "neutral",
        "illustrator": "Tim Durning",
        "is_loyal": false,
        "is_unique": false,
        "name": "The Brotherhood Without Banners",
        "octgn_id": null,
        "pack_code": "TBWB",
        "position": 119,
        "quantity": 3,
        "text": "You cannot include loyal character in your deck.\n<b>Reaction:</b> After the challenges phase begins, kneel your faction card to choose a neutral character you control. Until the end of the phase, that character gains (choose one): insight, intimidate, renown, or stealth.",
        "traits": "",
        "type_code": "agenda"
    }
]
